LICENSE.txt
README.md
setup.cfg
setup.py
pycorekit/ShellKit.py
pycorekit/__init__.py
pycorekit.egg-info/PKG-INFO
pycorekit.egg-info/SOURCES.txt
pycorekit.egg-info/dependency_links.txt
pycorekit.egg-info/requires.txt
pycorekit.egg-info/top_level.txt