Metadata-Version: 2.1
Name: pycorekit
Version: 0.0.6
Summary: An underlying tool library that can be used by any script
Home-page: https://github.com/MeDeity/core-kit
Author: MeDeity
Author-email: langrenbule@gmail.com
Classifier: Programming Language :: Python :: 3
Classifier: License :: OSI Approved :: MIT License
Classifier: Operating System :: OS Independent
Requires-Python: >=3.6
License-File: LICENSE.txt
